[
{ "id": "@Lang", "label": "Lang", "type": "string", "size": 30 },
{ "id": "@anid", "label": "anid", "type": "string", "size": 30 },
{ "id": "@V7", "label": "V7", "type": "string", "size": 30 },
{ "id": "@sr", "label": "sr", "type": "string", "size": 30 },
{ "id": "@vip", "label": "vip", "type": "string", "size": 30 },
{ "id": "@cip", "label": "cip", "type": "string", "size": 30 },
{ "id": "@real", "label": "real", "type": "string", "size": 30 },
{ "id": "@flag", "label": "flag", "type": "string", "size": 30 },
{ "id": "@Domain", "label": "Domain", "type": "string", "size": 30 },
{ "id": "@IC", "label": "IC", "type": "string", "size": 30 },
{ "id": "@MKW", "label": "MKW", "type": "string", "size": 30 },
{ "id": "@Reftype", "label": "Reftype", "type": "string", "size": 30 },
{ "id": "@SearchLang", "label": "SearchLang", "type": "string", "size": 30 },
{ "id": "@SearchTerm", "label": "SearchTerm", "type": "string", "size": 30 },
{ "id": "@Country", "label": "Country", "type": "string", "size": 30 },
{ "id": "@isWin", "label": "isWin", "type": "string", "size": 30 },
{ "id": "@version", "label": "version", "type": "string", "size": 30 },
{ "id": "@currency", "label": "currency", "type": "string", "size": 30 },
{ "id": "@gpr", "label": "gpr", "type": "string", "size": 30 }
]